gr4vy/__init__.py
gr4vy/_hooks/__init__.py
gr4vy/_hooks/sdkhooks.py
gr4vy/_hooks/types.py
gr4vy/_version.py
gr4vy/account_updater.py
gr4vy/actions.py
gr4vy/all.py
gr4vy/audit_logs.py
gr4vy/auth.py
gr4vy/balances.py
gr4vy/basesdk.py
gr4vy/buyers_gift_cards.py
gr4vy/buyers_payment_methods.py
gr4vy/buyers_sdk.py
gr4vy/buyers_shipping_details.py
gr4vy/card_scheme_definitions_sdk.py
gr4vy/checkout_sessions.py
gr4vy/digital_wallets_sdk.py
gr4vy/domains.py
gr4vy/errors/__init__.py
gr4vy/errors/apierror.py
gr4vy/errors/error400.py
gr4vy/errors/error401.py
gr4vy/errors/error403.py
gr4vy/errors/error404.py
gr4vy/errors/error405.py
gr4vy/errors/error409.py
gr4vy/errors/error425.py
gr4vy/errors/error429.py
gr4vy/errors/error500.py
gr4vy/errors/error502.py
gr4vy/errors/error504.py
gr4vy/errors/gr4vyerror.py
gr4vy/errors/httpvalidationerror.py
gr4vy/errors/no_response_error.py
gr4vy/errors/responsevalidationerror.py
gr4vy/events.py
gr4vy/executions.py
gr4vy/gift_cards_sdk.py
gr4vy/httpclient.py
gr4vy/jobs.py
gr4vy/merchant_accounts_sdk.py
gr4vy/models/__init__.py
gr4vy/models/accountsreceivablesreportspec.py
gr4vy/models/accountupdaterinquirysummary.py
gr4vy/models/accountupdaterjob.py
gr4vy/models/accountupdaterjobcreate.py
gr4vy/models/accountupdateroptions.py
gr4vy/models/add_buyer_shipping_detailsop.py
gr4vy/models/add_buyerop.py
gr4vy/models/add_payment_linkop.py
gr4vy/models/add_reportop.py
gr4vy/models/address.py
gr4vy/models/adyenautorescuesepascenariosenum.py
gr4vy/models/adyencardautorescuescenariosenum.py
gr4vy/models/adyencardoptions.py
gr4vy/models/adyenoptions.py
gr4vy/models/adyensepaoptions.py
gr4vy/models/adyensplitsoptions.py
gr4vy/models/affirmitineraryoptions.py
gr4vy/models/affirmoptions.py
gr4vy/models/airline.py
gr4vy/models/airlineleg.py
gr4vy/models/airlinepassenger.py
gr4vy/models/antifrauddecision.py
gr4vy/models/applepaypaymentmethodcreate.py
gr4vy/models/applepaysessionrequest.py
gr4vy/models/approvaltarget.py
gr4vy/models/auditlogaction.py
gr4vy-1.10.12.dist-info/METADATA
gr4vy-1.10.12.dist-info/WHEEL
gr4vy-1.10.12.dist-info/RECORD
