Metadata-Version: 2.4
Name: gr4vy
Version: 1.10.12
Summary: Python Client SDK Generated by Speakeasy.
Author: Gr4vy
Requires-Python: >=3.9.2
Classifier: Programming Language :: Python :: 3
Classifier: Programming Language :: Python :: 3.10
Classifier: Programming Language :: Python :: 3.11
Classifier: Programming Language :: Python :: 3.12
Classifier: Programming Language :: Python :: 3.13
Classifier: Programming Language :: Python :: 3.14
Requires-Dist: PyJWT (>=2.10.1,<3.0.0)
Requires-Dist: cryptography (>=45.0.7,<46.0.0)
Requires-Dist: httpcore (>=1.0.9)
Requires-Dist: httpx (>=0.28.1)
Requires-Dist: jsonpath-python (>=1.0.6)
Requires-Dist: pydantic (>=2.11.2)
Requires-Dist: python-jose (>=3.4.0,<4.0.0)
Project-URL: Repository, https://github.com/gr4vy/gr4vy-python.git
